<ann><anime id="2575" gid="2652807386" type="special" name="Mahoromatic: Summer Special" precision="special" generated-on="2016-03-27T02:38:43Z">
<related-prev rel="side story of" id="786"/>
<info gid="2900689540" type="Picture" src="http://cdn.animenewsnetwork.com/thumbnails/fit200x200/encyc/A2575-5.jpg" width="138" height="200"><img src="http://cdn.animenewsnetwork.com/thumbnails/fit200x200/encyc/A2575-5.jpg" width="138" height="200"/><img src="http://cdn.animenewsnetwork.com/thumbnails/max500x600/encyc/A2575-5.jpg" width="315" height="455"/></info>
<info gid="2579065330" type="Main title" lang="EN">Mahoromatic: Summer Special</info>
<info gid="909017048" type="Alternative title" lang="EN">Mahoromatic Natsu no TV Special</info>
<info gid="1734887306" type="Alternative title" lang="EN">Mahoromatic Summer 2003 TV Special</info>
<info gid="1732643382" type="Alternative title" lang="JA">まほろまてぃっく 夏のTVスペシャル</info>
<info gid="2012917851" type="Alternative title" lang="ZH-TW">魔力女管家特別篇</info>
<info gid="1760479118" type="Genres">comedy</info>
<info gid="930758261" type="Genres">science fiction</info>
<info gid="2868354038" type="Objectionable content">MA</info>
<info gid="2791599802" type="Plot Summary">It's another normal day in the Misato residence when Mahoro finds yet another pornographic magazine in Suguru's room. This prompts her and Minawa to make a pact with Chizuko, Rin, Miyuki and Miss Shikijo to search and confiscate all of the perverted stash in the house. Suguru, Kiyomi and Toshiya must do whatever it takes to protect their treasure from the girls.</info>
<info gid="2819920444" type="Running time">24</info>
<info gid="3400836428" type="Vintage">2003-08-15</info>
<info gid="2661559272" type="Opening Theme">&quot;そ・れ・い・ゆ (&lt;i&gt;Soreiyu&lt;/i&gt; - Soleil)&quot; by Ayako Kawasumi</info>
<info gid="2151968629" type="Ending Theme">&quot;Hiryu Musume Ha! Date Ondo&quot; by Triomatic and Minawa</info>
<info gid="3080878866" type="Official website" lang="JA" href="http://www.gainax.co.jp/anime/mahoro/index.html">GAINAX's Official Mahoromatic Site</info>
<info gid="2130727786" type="Official website" lang="EN" href="http://mahoromatic.pioneeranimation.com/">Geneon Entertainment's Official &lt;i&gt;Mahoromatic&lt;/i&gt; Homepage</info>
<info gid="3510017259" type="Official website" lang="JA" href="http://www.mahoro-matic.com/">Mahoromatic Official Site</info>
<ratings nb_votes="771" weighted_score="7.1091" bayesian_score="7.11596"/>
<episode num="1">
<title gid="2650143004" lang="EN">All Dirty Thoughts are Bad!</title></episode>
<review href="http://www.animenewsnetwork.com/review/mahoromatic-summer-special/dvd">Mahoromatic: Summer Special DVD</review>
<release date="2012-07-10" href="http://www.animenewsnetwork.com/encyclopedia/releases.php?id=20694">Mahoromatic - Ultimate Collection (DVD)</release>
<release date="2004-05-18" href="http://www.animenewsnetwork.com/encyclopedia/releases.php?id=2486">Mahoromatic: Summer Special (DVD)</release>
<release date="2004-05-18" href="http://www.animenewsnetwork.com/encyclopedia/releases.php?id=2489">Mahoromatic: Summer Special - + Box + Figure (DVD)</release>
<release date="2011-02-07" href="http://www.animenewsnetwork.com/encyclopedia/releases.php?id=20955">Mahoromatic: Something More Beautiful - Complete 2nd Season + Summer Special (DVD 1-3)</release>
<news datetime="2003-04-14T17:21:17Z" href="http://www.animenewsnetwork.com/news/2003-04-14/new-anime-coming-to-japan">New Anime coming to Japan</news>
<news datetime="2009-08-22T08:56:39Z" href="http://www.animenewsnetwork.com/news/2009-08-22/mahoromatic/tadaima-okaeri-anime-to-debut-in-october">&lt;cite&gt;Mahoromatic: Tadaima Okaeri&lt;/cite&gt; Anime to Debut in October</news>
<staff gid="4055951630"><task>Director</task><person id="16139">Shouji Saeki</person></staff>
<staff gid="3332966876"><task>Script</task><person id="1517">Bunjuro Nakayama</person></staff>
<staff gid="3241101516"><task>Storyboard</task><person id="16139">Shouji Saeki</person></staff>
<staff gid="2763795429"><task>Music</task><person id="565">Toshio Masuda</person></staff>
<staff gid="3602421602"><task>Original Manga</task><person id="1517">Bunjuro Nakayama</person></staff>
<staff gid="2416070901"><task>Original Manga</task><person id="1518">Bow Ditama</person></staff>
<staff gid="2766576142"><task>Character Design</task><person id="1521">Kazuhiro Takamura</person></staff>
<staff gid="2315682286"><task>Art Director</task><person id="7353">Naoko Kosakabe</person></staff>
<staff gid="2616019922"><task>Chief Animation Director</task><person id="1521">Kazuhiro Takamura</person></staff>
<staff gid="2966633118"><task>Art design</task><person id="1522">Masahiro Sato</person></staff>
<staff gid="1179184347"><task>Sound Director</task><person id="979">Yoshikazu Iwanami</person></staff>
<cast gid="2784549901" lang="EN"><role>Slash</role><person id="1143">Lex Lang</person></cast>
<cast gid="1338415493" lang="EN"><role>Saori Shikijo</role><person id="1184">Wendee Lee</person></cast>
<cast gid="1580449087" lang="EN"><role>Kiyomi Kawahara</role><person id="1401">Ron Allen</person></cast>
<cast gid="1806594949" lang="EN"><role>Chizuko Oe</role><person id="2255">Rebecca Forstadt</person></cast>
<cast gid="2627569442" lang="EN"><role>Suguru Misato</role><person id="3676">David Umansky</person></cast>
<cast gid="1911140659" lang="EN"><role>Minawa Ando</role><person id="4018">Lara Jill Miller</person></cast>
<cast gid="2022204500" lang="EN"><role>Mahoro Ando</role><person id="4228">Ellen Wilkinson</person></cast>
<cast gid="1855741672" lang="EN"><role>Toshiya Hamaguchi</role><person id="5194">Dave Lelyveld</person></cast>
<cast gid="343350894" lang="EN"><role>Miyuki Sakura</role><person id="7125">Michelle Ruff</person></cast>
<cast gid="1884424409" lang="EN"><role>Minawa Ando</role><person id="12804">Willow Armstrong</person></cast>
<cast gid="2133947122" lang="EN"><role>Rin Todoroki</role><person id="66657">Midge Mayes</person></cast>
<cast gid="3680955056" lang="JA"><role>Kiyomi Kawahara</role><person id="520">Atsushi Kisaichi</person></cast>
<cast gid="493020951" lang="JA"><role>Mahoro Ando</role><person id="525">Ayako Kawasumi</person></cast>
<cast gid="193308326" lang="JA"><role>Suguru Misato</role><person id="1552">Fujiko Takimoto</person></cast>
<cast gid="1517261654" lang="JA"><role>Saori Shikijo</role><person id="2079">Yumi Takada</person></cast>
<cast gid="1130966689" lang="JA"><role>Rin Todoroki</role><person id="3585">Manabi Mizuno</person></cast>
<cast gid="2712490638" lang="JA"><role>Miyuki Sakura</role><person id="3679">Yumi Kikuchi</person></cast>
<cast gid="1626779765" lang="JA"><role>Chizuko Oe</role><person id="3680">Asami Sanada</person></cast>
<cast gid="583691514" lang="JA"><role>Slash</role><person id="4274">Keiichi Noda</person></cast>
<cast gid="1493259098" lang="JA"><role>Toshiya Hamaguchi</role><person id="7350">Hideki Ogihara</person></cast>
<cast gid="2781422977" lang="JA"><role>Minawa Ando</role><person id="7592">Ai Shimizu</person></cast>
<credit gid="1092494345"><task>Animation Production</task><company id="677">SHAFT</company></credit>
<credit gid="2331075191"><task>Production</task><company id="49">TBS</company></credit>
<credit gid="1049061216"><task>Production</task><company id="54">GAINAX</company></credit>
<credit gid="2841655652"><task>Production</task><company id="2151">Geneon Entertainment, Inc.</company></credit>
<credit gid="291046556"><task>Production</task><company id="2651">Wani Books</company></credit>
<credit gid="1217275547"><task>Production</task><company id="2706">Mahoromatic Production Committee</company></credit></anime></ann>