<ann><anime id="2957" gid="1007208905" type="TV" name="PoPoLoCrois" precision="TV" generated-on="2016-03-27T03:52:17Z">
<related-prev rel="sequel of" id="1792"/>
<info gid="3437211062" type="Picture" src="http://cdn.animenewsnetwork.com/thumbnails/fit200x200/encyc/A2957-9.jpg" width="174" height="200"><img src="http://cdn.animenewsnetwork.com/thumbnails/fit200x200/encyc/A2957-9.jpg" width="174" height="200"/><img src="http://cdn.animenewsnetwork.com/thumbnails/max500x600/encyc/A2957-9.jpg" width="268" height="308"/></info>
<info gid="3042589096" type="Main title" lang="EN">PoPoLoCrois</info>
<info gid="1422224212" type="Alternative title" lang="JA">ポポロクロイス</info>
<info gid="2408105060" type="Genres">adventure</info>
<info gid="538836245" type="Genres">fantasy</info>
<info gid="1668535025" type="Plot Summary">Pinon, the boy who flows within his body, the blood of the three races (the Dragons, the fairies and the humans), is actually the son of the Courageous One, Pietro. Pinon's encounter with a mysterious animal, Pap, opens up the door to an adventurous journey. He befriends Luna and Marco on the way. However, when he learns that his adventure will determine the fate of PoPoLoCrois, Pinon hardens his heart and leaves his friends. Unknown to him, this is an introductory chapter to a new adventure and Pinon will realise that he must resolve the bigger crisis present in PoPoLoCrois.</info>
<info gid="3865708021" type="Running time">23</info>
<info gid="1722334859" type="Number of episodes">26</info>
<info gid="1404353114" type="Vintage">2003-10-05 to 2004-03-28</info>
<info gid="2033551564" type="Opening Theme">&quot;Tomodachi no Uta&quot; by CORE OF SOUL</info>
<info gid="2301638459" type="Ending Theme">&quot;Sakurami Oka&quot; by Local Bus</info>
<info gid="2879158277" type="Official website" lang="JA" href="http://www.tms-e.com/library/on_air_back/poporo/">ポポロクロイス @ TMS Entertainment</info>
<ratings nb_votes="19" weighted_score="4.929" bayesian_score="5.98277"/>
<episode num="1">
<title gid="1948134087" lang="EN">Adventure of the Dragon Shrine</title></episode>
<episode num="2">
<title gid="2192398672" lang="EN">Luna and the Golden Key</title></episode>
<episode num="3">
<title gid="2672032405" lang="EN">Adventure of the Sacred Castle of the Wind</title></episode>
<episode num="4">
<title gid="2491158813" lang="EN">Adventure of Takinen Valley</title></episode>
<episode num="5">
<title gid="2995413844" lang="EN">Adventure of the Castle of Flame</title></episode>
<episode num="6">
<title gid="2052610089" lang="EN">Castle of the Demon King, Gamigami</title></episode>
<episode num="7">
<title gid="760362303" lang="EN">Marco's Adventure</title></episode>
<episode num="8">
<title gid="1399450649" lang="EN">Monsters' Battle Meet</title></episode>
<episode num="9">
<title gid="1680772688" lang="EN">Adventure of the Sacred Castle of Water</title></episode>
<episode num="10">
<title gid="1895085130" lang="EN">Adventure of Dragon Shrine again</title></episode>
<episode num="11">
<title gid="3008174389" lang="EN">Adventure of the Sacred Castle of the Dark</title></episode>
<episode num="12">
<title gid="434968252" lang="EN">Last Battle</title></episode>
<episode num="13">
<title gid="153310559" lang="EN">Adventure in the Midst of Emotions</title></episode>
<episode num="14">
<title gid="2064013275" lang="EN">Adventure of the Golden Key</title></episode>
<episode num="15">
<title gid="320103567" lang="EN">Adventure of No. Dagart</title></episode>
<episode num="16">
<title gid="971129450" lang="EN">Test of Courage of the Sea</title></episode>
<episode num="17">
<title gid="2683112092" lang="EN">Adventure of the Marina Castle</title></episode>
<episode num="18">
<title gid="1226500034" lang="EN">Adventure of the Drops of Moon</title></episode>
<episode num="19">
<title gid="604539310" lang="EN">Adventure of Kaioumaru</title></episode>
<episode num="20">
<title gid="1193663310" lang="EN">Adventure of Coroconatia</title></episode>
<episode num="21">
<title gid="2324121529" lang="EN">Adventure of the Cave of Trial</title></episode>
<episode num="22">
<title gid="2950086356" lang="EN">Adventure of Remnas</title></episode>
<episode num="23">
<title gid="3160391437" lang="EN">Adventure of the Fossil Island</title></episode>
<episode num="24">
<title gid="399160965" lang="EN">The Adventure of Goodbye</title></episode>
<episode num="25">
<title gid="1595131688" lang="EN">Spirit King of the Dark</title></episode>
<episode num="26">
<title gid="1053737953" lang="EN">Law of the Moon</title></episode>
<staff gid="2781994259"><task>Director</task><person id="6575">Kazuhiro Ochi</person></staff>
<staff gid="3780659503"><task>Series Composition</task><person id="110">Reiko Yoshida</person></staff>
<staff gid="421653115"><task>Screenplay</task><person id="110">Reiko Yoshida</person></staff>
<staff gid="2224123255"><task>Screenplay</task><person id="4629">Natsuko Takahashi</person></staff>
<staff gid="1409916131"><task>Screenplay</task><person id="32136">Masahiro Yokotani</person></staff>
<staff gid="3041430939"><task>Screenplay</task><person id="39695">Mari Okada</person></staff>
<staff gid="1000834169"><task>Storyboard</task><person id="1734">Yoshinori Kanada</person></staff>
<staff gid="2386865042"><task>Storyboard</task><person id="3896">Kazu Yokota</person></staff>
<staff gid="2376665053"><task>Storyboard</task><person id="10364">Yuzo Aoki</person></staff>
<staff gid="2069399464"><task>Storyboard</task><person id="11986">Minoru Ohara</person></staff>
<staff gid="2387454793"><task>Storyboard</task><person id="12411">Kazuo Nogami</person></staff>
<staff gid="2466630205"><task>Storyboard</task><person id="43192">Yasuyuki Honda</person></staff>
<staff gid="3052246049"><task>Storyboard</task><person id="128474">Seiji Okuda</person></staff>
<staff gid="3840929015"><task>Episode Director</task><person id="3896">Kazu Yokota</person></staff>
<staff gid="1363784317"><task>Episode Director</task><person id="11986">Minoru Ohara</person></staff>
<staff gid="2083037103"><task>Episode Director</task><person id="12411">Kazuo Nogami</person></staff>
<staff gid="1948689937"><task>Episode Director</task><person id="12453">Shigeki Takagi</person></staff>
<staff gid="2968385163"><task>Episode Director</task><person id="30338">Yoshiaki Okumura</person></staff>
<staff gid="3216661918"><task>Episode Director</task><person id="43194">Tomomasa Yamazaki</person></staff>
<staff gid="3142444402"><task>Episode Director</task><person id="43195">Yasuyuki Shinozaki</person></staff>
<staff gid="2502025165"><task>Music</task><person id="23460">Koichiro Kameyama</person></staff>
<staff gid="1100321372"><task>Original creator</task><person id="37516">Yousuke Tamori</person></staff>
<staff gid="2847134970"><task>Character Design</task><person id="2771">Atsuko Fukushima</person></staff>
<staff gid="409185054"><task>Art Director</task><person id="8842">Katsufumi Hariu</person></staff>
<staff gid="1875969796"><task>Animation Director</task><person id="14">Minoru Maeda</person></staff>
<staff gid="2268433658"><task>Animation Director</task><person id="14429">Yoshiharu Shimizu</person></staff>
<staff gid="2982177560"><task>Animation Director</task><person id="15694">Ichiro Ogawa</person></staff>
<staff gid="320723335"><task>Animation Director</task><person id="22429">Mitsuru Soma</person></staff>
<staff gid="2406276855"><task>Animation Director</task><person id="35263">Satoru Hirayama</person></staff>
<staff gid="1935141007"><task>Animation Director</task><person id="41457">Kinomi Sakurai</person></staff>
<staff gid="1189015925"><task>Animation Director</task><person id="43090">Kei Takeuchi</person></staff>
<staff gid="2446151096"><task>Sound Director</task><person id="43164">Keiichiro Miyoshi</person></staff>
<staff gid="726233624"><task>Director of Photography</task><person id="6550">Hitoshi Shirao</person></staff>
<staff gid="2054690671"><task>Producer</task><person id="7588">Tetsuya Watanabe</person></staff>
<staff gid="3614544934"><task>Producer</task><person id="13328">Norio Yamakawa</person></staff>
<staff gid="2199677733"><task>Producer</task><person id="13571">Hideaki Miyamoto</person></staff>
<cast gid="950078712" lang="JA"><role>Pietro</role><person id="832">Akio Ohtsuka</person></cast>
<cast gid="1122492481" lang="JA"><role>Pap</role><person id="846">Ikue Ohtani</person></cast>
<cast gid="2083367217" lang="JA"><role>Marco</role><person id="1307">Wataru Takagi</person></cast>
<cast gid="3185141913" lang="JA"><role>Pinon</role><person id="1500">Omi Minami</person></cast>
<cast gid="2246167890" lang="JA"><role>Luna</role><person id="1555">Tomoe Hanba</person></cast>
<cast gid="270934976" lang="JA"><role>Narcia</role><person id="1577">Maria Kawamura</person></cast>
<cast gid="1984188805" lang="TL"><role>Marco</role><person id="38929">Montreal Repuyan</person></cast>
<cast gid="3036297760" lang="TL"><role>Pietro</role><person id="38929">Montreal Repuyan</person></cast>
<cast gid="1479119032" lang="TL"><role>Luna</role><person id="38931">Filipina Pamintuan</person></cast>
<cast gid="3255789169" lang="TL"><role>Elena</role><person id="39024">Grace Cornel</person></cast>
<cast gid="497900483" lang="TL"><role>Pinon</role><person id="39024">Grace Cornel</person></cast>
<cast gid="2405660839" lang="TL"><role>Narcia</role><person id="42182">Rowena Raganit</person></cast>
<cast gid="2416512513" lang="TL"><role>Papu</role><person id="42182">Rowena Raganit</person></cast>
<cast gid="921578339" lang="TL"><role>Selena</role><person id="42182">Rowena Raganit</person></cast>
<credit gid="2153332336"><task>Production</task><company id="249">Dentsu Inc.</company></credit>
<credit gid="3237572931"><task>Production</task><company id="292">TMS Entertainment</company></credit></anime></ann>