<ann><anime id="301" gid="2921749869" type="OAV" name="Bubblegum Crash" precision="OAV" generated-on="2016-03-27T03:55:01Z">
<related-prev rel="sequel of" id="201"/>
<info gid="2232076751" type="Picture" src="http://cdn.animenewsnetwork.com/thumbnails/fit200x200/encyc/A301-2232076751.1429633711.jpg" width="136" height="200"><img src="http://cdn.animenewsnetwork.com/thumbnails/fit200x200/encyc/A301-2232076751.1429633711.jpg" width="136" height="200"/><img src="http://cdn.animenewsnetwork.com/thumbnails/max500x600/encyc/A301-2232076751.1429633711.jpg" width="407" height="600"/><img src="http://cdn.animenewsnetwork.com/images/encyc/A301-2232076751.1429633711.jpg" width="542" height="800"/></info>
<info gid="3200939742" type="Main title" lang="EN">Bubblegum Crash</info>
<info gid="1772249018" type="Alternative title" lang="JA">バブルガム・クラッシュ!</info>
<info gid="2192541004" type="Genres">action</info>
<info gid="2251606759" type="Genres">science fiction</info>
<info gid="2844645523" type="Themes">mecha</info>
<info gid="1539870061" type="Objectionable content">TA</info>
<info gid="2919387420" type="Plot Summary">The saga of the Knight Sabers continues as the group tries to find out who or what is behind the recent string of robberies, murders, and Boomer malfunctions which are somehow related to the creation of an advanced artificial intelligence. Furthermore, it seems that the Knight Sabers may be breaking up.</info>
<info gid="1184313684" type="Running time">45</info>
<info gid="2903890626" type="Number of episodes">3</info>
<info gid="792252677" type="Vintage">1991</info>
<info gid="1763022586" type="Opening Theme">&quot;Hateshinai Tabi - Hajimari no Toki&quot; (果てない旅 ~始まりの時) by Ryoko Tachikawa</info>
<info gid="1305847234" type="Ending Theme">#1: &quot;Cool Eyes&quot; by Ryoko Tachikawa (ep 1)</info>
<info gid="2851182651" type="Ending Theme">#2: &quot;Saigo ni...&quot; (最後に…) by Ryoko Tachikawa (ep 2)</info>
<info gid="2398167799" type="Ending Theme">#3: &quot;Over the Pressure - Toki o Koete&quot; (OVER THE PRESSURE~時を越えて) by Knight Sabers (ep 3)</info>
<info gid="146064131" type="Official website" lang="EN" href="http://www.aicanime.com/products/bgc/index.html">AIC's Official Bubblegum Crash Homepage</info>
<ratings nb_votes="352" weighted_score="6.2802" bayesian_score="6.32446"/>
<episode num="1">
<title gid="3861329539" lang="EN">Illegal Army</title></episode>
<episode num="2">
<title gid="1247569393" lang="EN">Geo Climbers</title></episode>
<episode num="3">
<title gid="2653758471" lang="EN">Melt Down</title></episode>
<review href="http://www.animenewsnetwork.com/review/bubblegum-crash/dvd">Bubblegum Crash DVD</review>
<release date="2001-12-18" href="http://www.animenewsnetwork.com/encyclopedia/releases.php?id=434">Bubblegum Crash - Total Crash Collection (DVD)</release>
<news datetime="2001-04-17T03:52:12Z" href="http://www.animenewsnetwork.com/news/2001-04-16/animeigo-slashes-prices-spirit-of-wonder-out-of-print">AnimEigo Slashes Prices, Spirit of Wonder Out of Print</news>
<news datetime="2001-10-15T05:56:56Z" href="http://www.animenewsnetwork.com/news/2001-10-15/seiyuu-michie-tomizawa-to-retire">Seiyuu Michie Tomizawa to Retire</news>
<staff gid="3116289896"><task>Director</task><person id="588">Hiroyuki Fukushima</person></staff>
<staff gid="515391304"><task>Director</task><person id="8561">Hiroshi Ishiodori</person></staff>
<staff gid="1582826271"><task>Screenplay</task><person id="8560">Emu Arii</person></staff>
<staff gid="1940711178"><task>Storyboard</task><person id="588">Hiroyuki Fukushima</person></staff>
<staff gid="724990516"><task>Storyboard</task><person id="8561">Hiroshi Ishiodori</person></staff>
<staff gid="3528484465"><task>Music</task><person id="8562">Takehito Nakazawa</person></staff>
<staff gid="3820188915"><task>Music</task><person id="8563">Michihiko Oota</person></staff>
<staff gid="857134411"><task>Music</task><person id="146791">Takumi Kawai</person></staff>
<staff gid="2006439213"><task>Original story</task><person id="990">Toshimichi Suzuki</person></staff>
<staff gid="1894713841"><task>Character Design</task><person id="102">Kenichi Sonoda</person></staff>
<staff gid="3720217467"><task>Character Design</task><person id="541">Hiroaki Gohda</person></staff>
<staff gid="1802970257"><task>Executive producer</task><person id="990">Toshimichi Suzuki</person></staff>
<cast gid="2066016022" lang="EN"><role>Linna Yamazaki</role><person id="1056">Elizabeth Becka</person></cast>
<cast gid="3373595663" lang="EN"><role>Nene Romanova</role><person id="1058">Susan Grillo</person></cast>
<cast gid="883579323" lang="EN"><role>Leon McNichol</role><person id="1059">Brad Moranz</person></cast>
<cast gid="2099151928" lang="EN"><role>Priscilla S. &quot;Priss&quot; Asagiri</role><person id="1060">Sinda Nichols</person></cast>
<cast gid="2653980563" lang="EN"><role>Mackie Stingray</role><person id="1061">Frank Trimble</person></cast>
<cast gid="2867049182" lang="EN"><role>as Linna Yamazaki</role><person id="3274">Stacey Gregg</person></cast>
<cast gid="2305514382" lang="EN"><role>as Priscilla S. &quot;Priss&quot; Asagiri</role><person id="3276">Julia Brahms</person></cast>
<cast gid="3134325355" lang="EN"><role>as Sylia Stingray</role><person id="6769">Tamsin Hollo</person></cast>
<cast gid="1231173363" lang="EN"><role>Daley Wong</role><person id="10684">Marshall Carroll</person></cast>
<cast gid="2359663826" lang="EN"><role>Sylia Stingray</role><person id="10686">Jemila Ericson</person></cast>
<cast gid="306076544" lang="EN"><role>Largo/Mystery Man</role><person id="10691">Pierre Brulator</person></cast>
<cast gid="1128309424" lang="ES"><role>Leon McNichol</role><person id="31677">Tasio Alonso</person></cast>
<cast gid="1013553528" lang="ES"><role>Ralgo</role><person id="32388">Carlos Lladó</person></cast>
<cast gid="1032648551" lang="ES"><role>Priscilla S. &quot;Priss&quot; Asagiri</role><person id="50521">Maria Rosa Guillén</person></cast>
<cast gid="2849198222" lang="ES"><role>Linna Yamazaki</role><person id="50562">Carmen Calvell</person></cast>
<cast gid="2792198762" lang="ES"><role>Nene Romanova</role><person id="50568">Ariadna Jiménez</person></cast>
<cast gid="2275224886" lang="ES"><role>Sylia Stingray</role><person id="72801">Sofia Garcia</person></cast>
<cast gid="782891117" lang="ES"><role>Daley Wong</role><person id="118959">Jordi Naro</person></cast>
<cast gid="2250331872" lang="JA"><role>Linna Yamazaki</role><person id="297">Michie Tomizawa</person></cast>
<cast gid="2929740851" lang="JA"><role>Nene Romanova</role><person id="854">Akiko Hiramatsu</person></cast>
<cast gid="2067950888" lang="JA"><role>Leon McNichol</role><person id="1011">Toshio Furukawa</person></cast>
<cast gid="809032342" lang="JA"><role>Mackie Stingray</role><person id="1012">Nozomu Sasaki</person></cast>
<cast gid="1764591966" lang="JA"><role>Sylia Stingray</role><person id="1022">Yoshiko Sakakibara</person></cast>
<cast gid="2340515046" lang="JA"><role>Daley Wong</role><person id="1177">Kenyuu Horiuchi</person></cast>
<cast gid="2645027683" lang="JA"><role>Largo (Mystery Voice)</role><person id="1614">Kazuyuki Sogabe</person></cast>
<cast gid="1131188712" lang="JA"><role>Priscilla S. &quot;Priss&quot; Asagiri</role><person id="2395">Ryoko Tachikawa</person></cast>
<credit gid="2404400487"><task>Production</task><company id="312">Artland</company></credit>
<credit gid="446508924"><task>Production</task><company id="711">JVC</company></credit>
<credit gid="3003314133"><task>Production</task><company id="786">DARTS</company></credit>
<credit gid="1120872162"><task>Production</task><company id="818">ARTMIC Studios</company></credit></anime></ann>