<ann><anime id="3158" gid="2420474769" type="OAV" name="Karen" precision="OAV" generated-on="2016-03-27T03:57:02Z">
<related-prev rel="adapted from" id="12892"/>
<info gid="1075070728" type="Picture" src="http://cdn.animenewsnetwork.com/thumbnails/fit200x200/encyc/A3158-11.jpg" width="172" height="200"><img src="http://cdn.animenewsnetwork.com/thumbnails/fit200x200/encyc/A3158-11.jpg" width="172" height="200"/></info>
<info gid="1647183373" type="Main title" lang="EN">Karen</info>
<info gid="3142595598" type="Alternative title" lang="JA">カレン</info>
<info gid="3889892775" type="Genres">drama</info>
<info gid="1671801469" type="Genres">erotica</info>
<info gid="2423490938" type="Objectionable content">AO</info>
<info gid="2134998182" type="Plot Summary">Ryo, the first female captain of the university's cheering squad, wants to come to terms with its members after they threaten to quit. They respond by setting up a number of perverted challenges for her to go through. Ryo must accept these obstacles while keeping the team and her sanity in check.</info>
<info gid="1677928293" type="Running time">29</info>
<info gid="1137802546" type="Number of episodes">1</info>
<info gid="2300730868" type="Vintage">2002-07-18 (Japan)</info>
<ratings nb_votes="55" weighted_score="5.6816" bayesian_score="6.03361"/>
<release date="2008-05-27" href="http://www.animenewsnetwork.com/encyclopedia/releases.php?id=12327">Karen (DVD)</release>
<staff gid="1278388386"><task>Director</task><person id="30575">Shinichi Shimizu</person></staff>
<staff gid="3154541423"><task>Script</task><person id="30576">Oansu Ban</person></staff>
<staff gid="3530262727"><task>Original Manga</task><person id="19098">Kyouta Izumi</person></staff>
<staff gid="1225714759"><task>Character Design</task><person id="19099">TAKA</person></staff>
<staff gid="2817770464"><task>Art Director</task><person id="8876">Hitoshi Nagao</person></staff>
<staff gid="2475436317"><task>Animation Director</task><person id="27640">Akira Nakamura</person></staff>
<staff gid="2084592467"><task>Producer</task><person id="30577">Masayuki Nagata</person></staff>
<cast gid="3829811599" lang="JA"><role>Doshima</role><person id="1036">Takehiro Murozono</person></cast>
<cast gid="909923097" lang="JA"><role>Ryo Okawa</role><person id="44574">Saki Mimura</person></cast>
<cast gid="1669747366" lang="JA"><role>Aki</role><person id="44575">Aki Fujimura</person></cast>
<credit gid="2061704868"><task>Production</task><company id="1169">Five Ways</company></credit>
<credit gid="1789109755"><task>Production</task><company id="1894">T.I. Net</company></credit></anime></ann>