<ann><anime id="3259" gid="2732239658" type="OAV" name="Green Green Character DVD" precision="OAV" generated-on="2016-03-27T02:20:15Z">
<related-prev rel="spinoff of" id="2291"/>
<info gid="1198300658" type="Main title" lang="EN">Green Green Character DVD</info>
<info gid="2171479187" type="Alternative title" lang="JA">グリーングリーンキャラクターDVD</info>
<info gid="228503921" type="Genres">comedy</info>
<info gid="3695596905" type="Genres">erotica</info>
<info gid="2409779983" type="Themes">ecchi</info>
<info gid="184330758" type="Themes">fanservice</info>
<info gid="1884801494" type="Objectionable content">MA</info>
<info gid="2085664509" type="Plot Summary">Just a mini-game where you have to guess with character is at the screen by only seeing small parts (big some times) of it.</info>
<info gid="3213457696" type="Number of episodes">3</info>
<info gid="843665448" type="Vintage">2003-11-19</info>
<info gid="1612160270" type="Official website" lang="JA" href="http://www.ponycanyon.co.jp/greengreen/">Green Green Official Site</info>
<ratings nb_votes="132" weighted_score="6.1678" bayesian_score="6.28929"/>
<episode num="1">
<title gid="1374717892" lang="EN">Sanae &amp; Wakaba</title></episode>
<episode num="2">
<title gid="1303064174" lang="EN">Futaba &amp; Chigusa</title></episode>
<episode num="3">
<title gid="2560530990" lang="EN">Midori &amp; Reika</title></episode>
<cast gid="2746808980" lang="JA"><role>Chigusa Iino</role><person id="517">Mariko Suzuki</person></cast>
<cast gid="3509364815" lang="JA"><role>Reika Morimura</role><person id="1568">Kana Ueda</person></cast>
<cast gid="1706257417" lang="JA"><role>Sanae Minami</role><person id="9192">Saori Suzuki</person></cast>
<cast gid="3538136318" lang="JA"><role>Wakaba Kutsuki</role><person id="9921">Yukiko Mannaka</person></cast>
<cast gid="3109723762" lang="JA"><role>Midori Chitose</role><person id="12646">Sara Nakayama</person></cast>
<cast gid="865166907" lang="JA"><role>Futaba Kutsuki</role><person id="12730">Eriko Fujimaki</person></cast>
<credit gid="1812932920"><task>Animation Production</task><company id="1076">Studio Matrix</company></credit></anime></ann>