<ann><anime id="5385" gid="3248251445" type="movie" name="Welcome to Lodoss Island!" precision="movie" generated-on="2016-03-27T03:57:34Z">
<related-prev rel="adapted from" id="3067"/>
<info gid="3112041116" type="Picture" src="http://cdn.animenewsnetwork.com/thumbnails/fit200x200/encyc/A5385-3.jpg" width="200" height="133"><img src="http://cdn.animenewsnetwork.com/thumbnails/fit200x200/encyc/A5385-3.jpg" width="200" height="133"/></info>
<info gid="1368870879" type="Main title" lang="EN">Welcome to Lodoss Island!</info>
<info gid="1014908500" type="Alternative title" lang="JA">Yōkoso Lodoss Tō e!</info>
<info gid="3643321389" type="Alternative title" lang="JA">ようこそロードス島へ！</info>
<info type="Plot Summary">This series parodies the events of the Record of Lodoss series with the characters in chibi form. &lt;em class=de-emphasized&gt;(from manga)&lt;/em&gt;</info>
<info gid="1743852473" type="Running time">54</info>
<info type="Vintage">1998-04-25</info>
<info gid="1183505106" type="Premiere date">1998-04-25 (Japan)</info>
<ratings nb_votes="22" weighted_score="5.7607" bayesian_score="6.41523"/>
<staff gid="3162478202"><task>Director</task><person id="54">Koichi Chigira</person></staff>
<staff gid="2022437799"><task>Original creator</task><person id="2988">Ryo Mizuno</person></staff>
<staff gid="1038626987"><task>Original Manga</task><person id="4549">Rei Hyakuyashiki</person></staff>
<staff gid="3304992656"><task>Character Design</task><person id="4114">Koichi Usami</person></staff>
<staff gid="1464813778"><task>Character Design</task><person id="19996">Akemi Kobayashi</person></staff>
<staff gid="1143442863"><task>Animation Director</task><person id="4114">Koichi Usami</person></staff>
<staff gid="1660477386"><task>Animation Director</task><person id="19996">Akemi Kobayashi</person></staff>
<cast gid="2681124350" lang="JA"><role>Parn</role><person id="659">Shinichiro Miki</person></cast>
<cast gid="2420020215" lang="JA"><role>Deedlet</role><person id="828">Yuko Miyamura</person></cast></anime></ann>