<ann><anime id="746" gid="1712048240" type="TV" name="Sonic Soldier Borgman" precision="TV" generated-on="2016-03-27T03:55:19Z">
<related-next id="743" rel="sequel"/>
<info gid="2384116543" type="Picture" src="http://cdn.animenewsnetwork.com/thumbnails/fit200x200/encyc/A746-2384116543.1335219695.jpg" width="151" height="200"><img src="http://cdn.animenewsnetwork.com/thumbnails/fit200x200/encyc/A746-2384116543.1335219695.jpg" width="151" height="200"/><img src="http://cdn.animenewsnetwork.com/thumbnails/max500x600/encyc/A746-2384116543.1335219695.jpg" width="200" height="265"/></info>
<info gid="350769787" type="Main title" lang="EN">Sonic Soldier Borgman</info>
<info gid="2333702676" type="Alternative title" lang="EN">Borgman</info>
<info gid="851030860" type="Alternative title" lang="IT">Borgman 2030</info>
<info gid="2034022338" type="Alternative title" lang="JA">Chōon Senshi Borgman</info>
<info gid="1921761904" type="Alternative title" lang="JA">超音戦士ボーグマン</info>
<info gid="1842465117" type="Genres">action</info>
<info gid="2112662462" type="Genres">adventure</info>
<info gid="2164140344" type="Genres">science fiction</info>
<info gid="1109759480" type="Objectionable content">OC</info>
<info gid="1593341781" type="Plot Summary">AD 199X, Tokyo. Four giant meteorites appearing out of nowhere crash on the city, destroying much of it. Thirty years later, Tokyo has been completely rebuilt under the name of Megalocity, enojoying a high level of prosperity and technology. However, the city is often under attack from extradimensional creatures called Youmas, that seem somehow linked to the accident happened thirty years before. While the city police seems mostly helpless against those creatures, a group of cyborgs known as Borgman, Ryo Hibiki, Chuck Swegger and Anice Farm, fight off the Youmas using powered suits called baltectors. With the help of the scientist Memory Gene, the Borgman try to stop the Youmas and their enigmatic leader, Gilbert Mesh, from taking over Megalocity.</info>
<info gid="710795897" type="Running time">25</info>
<info gid="2752641027" type="Number of episodes">35</info>
<info gid="2347295069" type="Vintage">1988-04-13 to 1988-12-21</info>
<info gid="1222247626" type="Opening Theme">#1: &quot;Don't Look Back&quot; by Earthshaker</info>
<info gid="3819807434" type="Opening Theme">#2: &quot;Yoru o Futtobase&quot; by HIPS</info>
<info gid="697330038" type="Ending Theme">#1: &quot;Forever&quot; by Earthshaker</info>
<info gid="1006947181" type="Ending Theme">#2: &quot;Tender&quot; by HIPS</info>
<info gid="1778094684" type="Official website" lang="JA" href="http://www.pro-reed.com/works/tv_series/w015.html">超音戦士 ボーグマン｜作品紹介 : 株式会社 PRODUCTION REED</info>
<info gid="2654123263" type="Official website" lang="EN" href="http://www.pro-reed.com/works/tv_series/w015a.html">SONIC SOLDIER BORGMAN | WORKS : PRODUCTION REED CO.,LTD.</info>
<info gid="902821595" type="Official website" lang="JA" href="http://www.vap.co.jp/borgman/">=VAP= 『超音戦士ボーグマン』BD SONIC POWER COLLECTION</info>
<ratings nb_votes="13" weighted_score="6.5179" bayesian_score="7.0204"/>
<episode num="1">
<title gid="2563576343" lang="EN">The Youma has come. Borgman to set off!</title></episode>
<episode num="2">
<title gid="1290919963" lang="EN">Who's that? The 3rd Borgman</title></episode>
<episode num="3">
<title gid="1652841848" lang="EN">Destroy the bad dreams, Sonic Power!</title></episode>
<episode num="4">
<title gid="489106546" lang="EN">The Strongest Enemy! Dust Jead</title></episode>
<episode num="5">
<title gid="3488426092" lang="EN">Super Thunder, attack!</title></episode>
<episode num="6">
<title gid="254667770" lang="EN">Super Thunder versus Soulful Biker</title></episode>
<episode num="7">
<title gid="3010298210" lang="EN">A Youma's Mysterious World</title></episode>
<episode num="8">
<title gid="1886741726" lang="EN">Attack of the flowers! A girl saw a flower sprite!</title></episode>
<episode num="9">
<title gid="3789345036" lang="EN">Water race of Screaming Demons</title></episode>
<episode num="10">
<title gid="2120828747" lang="EN">Youma weapon! Youth from the past</title></episode>
<episode num="11">
<title gid="3946695037" lang="EN">Strongest power! Metal warrior appears</title></episode>
<episode num="12">
<title gid="2819537066" lang="EN">Escape from the Youma Stone</title></episode>
<episode num="13">
<title gid="2948177874" lang="EN">Bloody battle! The day of Ryou's death</title></episode>
<episode num="14">
<title gid="1193320549" lang="EN">Stand up, Ryou! Borgman's assasination</title></episode>
<episode num="15">
<title gid="3171303794" lang="EN">I saw it! Our teacher is a borgman</title></episode>
<episode num="16">
<title gid="2341949940" lang="EN">Beauty Trap! A film star's big pinch</title></episode>
<episode num="17">
<title gid="1974997656" lang="EN">Pierrot laughs! Strange occurances on Youma Land</title></episode>
<episode num="18">
<title gid="1942418896" lang="EN">Mystery of Mesh! When the Red Star falls</title></episode>
<episode num="19">
<title gid="2370790289" lang="EN">Youma City! Strange Country Anisu</title></episode>
<episode num="20">
<title gid="2734425244" lang="EN">The Warriors of Doctor Memory</title></episode>
<episode num="21">
<title gid="2331175508" lang="EN">Nightmare of a midsummer's night! A present from the Youma</title></episode>
<episode num="22">
<title gid="1805767611" lang="EN">Terror from the Sea! Our Adventure</title></episode>
<episode num="23">
<title gid="615524586" lang="EN">Rescue Shinji! Borgman Base under Attack</title></episode>
<episode num="24">
<title gid="2233360449" lang="EN">Clash! Phantom Swat VS Borgman</title></episode>
<episode num="25">
<title gid="1403889941" lang="EN">Trap of Terror, Death Match! Youma World</title></episode>
<episode num="26">
<title gid="2401525749" lang="EN">Desperate Escape! Youma General, the strongest enemy, appears</title></episode>
<episode num="27">
<title gid="943603815" lang="EN">Prelude of Destruction!</title></episode>
<episode num="28">
<title gid="2386543271" lang="EN">Annie's Decision! I will protect these children</title></episode>
<episode num="29">
<title gid="2487527043" lang="EN">Day of Destruction! Megalocity Crisis</title></episode>
<episode num="30">
<title gid="2287294317" lang="EN">Urgent Orders! Mobile Base Initiated</title></episode>
<episode num="31">
<title gid="1213524057" lang="EN">Desperation! Memory Confined</title></episode>
<episode num="32">
<title gid="3470186643" lang="JA">粉砕せよ!ギルトライアングル攻防戦</title></episode>
<episode num="33">
<title gid="1333582104" lang="EN">Youma Tower Appears! Countdown to the End</title></episode>
<episode num="34">
<title gid="2379556659" lang="EN">Cry out to the Sky! Dust Jead Dies</title></episode>
<episode num="35">
<title gid="2491091295" lang="EN">Youma King Resurrects! Goodbye, Borgman</title></episode>
<staff gid="1682462493"><task>Director</task><person id="68">Hiroshi Negishi</person></staff>
<staff gid="2981252584"><task>Series Composition</task><person id="3905">Hideki Sonoda</person></staff>
<staff gid="1085782103"><task>Storyboard</task><person id="30362">Shinsaku Kozuma</person></staff>
<staff gid="3373470635"><task>Music</task><person id="10820">Hiromoto Tobisawa</person></staff>
<staff gid="1308434449"><task>Character Design</task><person id="135">Koichi Ohata</person></staff>
<staff gid="758394562"><task>Character Design</task><person id="9697">Michitaka Kikuchi</person></staff>
<staff gid="3020930041"><task>Animation Director</task><person id="83">Kazuko Tadano</person></staff>
<staff gid="2474535779"><task>Mecha design</task><person id="135">Koichi Ohata</person></staff>
<staff gid="1980031774"><task>Mecha design</task><person id="5829">Takahiro Yamada</person></staff>
<staff gid="2168913265"><task>Mecha design</task><person id="10091">Hitoshi Fukuchi</person></staff>
<staff gid="1995885927"><task>Sound Director</task><person id="649">Katsunori Shimizu</person></staff>
<staff gid="1324150563"><task>Producer</task><person id="638">Toru Horikoshi</person></staff>
<staff gid="1692527753"><task>Producer</task><person id="8144">Minoru Ohno</person></staff>
<staff gid="2232940144"><task>Producer</task><person id="107459">Hiroshi Kato</person></staff>
<cast gid="1875429087" lang="IT"><role>Dust Jead</role><person id="18124">Claudio Moneta</person></cast>
<cast gid="2587418229" lang="IT"><role>Memory Gene</role><person id="25934">Roberta Gallina Laurenti</person></cast>
<cast gid="2764639764" lang="IT"><role>Gilbert Mesh</role><person id="26388">Augusto Di Bono</person></cast>
<cast gid="1739486534" lang="IT"><role>Anice Farm</role><person id="27340">Anna Lana</person></cast>
<cast gid="2682923575" lang="JA"><role>Ryō Hibiki</role><person id="499">Yasunori Matsumoto</person></cast>
<cast gid="3835701739" lang="JA"><role>Chuck Sweager</role><person id="722">Kazuhiko Inoue</person></cast>
<cast gid="1122030105" lang="JA"><role>Katsura Miki</role><person id="974">Naoko Matsui</person></cast>
<cast gid="870474107" lang="JA"><role>Dust Jead</role><person id="1009">Kouichi Yamadera</person></cast>
<cast gid="3029916157" lang="JA"><role>Memory Gene</role><person id="1046">Masako Katsuki</person></cast>
<cast gid="1524877351" lang="JA"><role>Anice Farm</role><person id="1588">Yoshino Takamori</person></cast>
<cast gid="2716164221" lang="JA"><role>Gilbert Mesh</role><person id="1669">Banjou Ginga</person></cast>
<cast gid="1161418478" lang="JA"><role>Shinji</role><person id="5082">Youko Ogai</person></cast>
<cast gid="3642375691" lang="JA"><role>Morley</role><person id="6993">Chie Koujiro</person></cast>
<credit gid="3012082019"><task>Production</task><company id="39">TOHO</company></credit>
<credit gid="399199317"><task>Production</task><company id="509">Ashi Productions</company></credit>
<credit gid="672891435"><task>Production</task><company id="863">Yomiuri Advertising</company></credit></anime></ann>