<ann><anime id="7846" gid="2171704083" type="OAV" name="Dead Girls" precision="OAV" generated-on="2016-03-27T01:50:40Z">
<related-prev rel="sequel of" id="6804"/>
<info gid="2426872421" type="Picture" src="http://cdn.animenewsnetwork.com/thumbnails/fit200x200/encyc/A7846-16.jpg" width="200" height="200"><img src="http://cdn.animenewsnetwork.com/thumbnails/fit200x200/encyc/A7846-16.jpg" width="200" height="200"/><img src="http://cdn.animenewsnetwork.com/thumbnails/max500x600/encyc/A7846-16.jpg" width="400" height="400"/></info>
<info gid="3392225527" type="Main title" lang="EN">Dead Girls</info>
<info gid="1607277830" type="Alternative title" lang="JA">デッドガールズ</info>
<info gid="2723176602" type="Genres">mystery</info>
<info gid="372508564" type="Themes">mecha</info>
<info gid="2101123232" type="Plot Summary">It's the future of New York. Kate, Rose, Rachel, and Claire lead the normal school life and a new transfer student comes... The transfer student, Louis wants to be friends with Kate. However, something happens to &quot;Red Garden&quot;. What is the truth behind this and the real purpose.</info>
<info gid="607330431" type="Running time">45</info>
<info gid="629191823" type="Number of episodes">1</info>
<info gid="2323931740" type="Vintage">2007-08-04 (limited net broadcasting on Gyao and Animate TV)</info>
<info gid="3594832268" type="Vintage">2007-08-05 (limited net broadcasting on Biglobe)</info>
<info gid="2568693511" type="Official website" lang="JA" href="http://www.trinet-ent.com/deadgirls/">Dead Girls OVA Official Website</info>
<info gid="2762550548" type="Official website" lang="EN" href="http://funimation.com/redgarden">Funimation's Official Red Garden Website</info>
<info gid="1682130079" type="Official website" lang="JA" href="http://www.gyao.jp/anime/deadgirls/">GyaO『デッドガールズ』</info>
<ratings nb_votes="190" weighted_score="6.206" bayesian_score="6.29033"/>
<staff gid="3209258080"><task>Director</task><person id="18133">Kou Matsuo</person></staff>
<staff gid="1454585713"><task>Screenplay</task><person id="39695">Mari Okada</person></staff>
<staff gid="2236148044"><task>Music</task><person id="17449">Akira Senju</person></staff>
<staff gid="2399375407"><task>Original Character Design</task><person id="58727">Fujijun</person></staff>
<staff gid="2793975894"><task>Character Design</task><person id="15805">Kumi Ishii</person></staff>
<staff gid="1492259829"><task>Art Director</task><person id="6508">Masatoshi Kai</person></staff>
<staff gid="3835932059"><task>Chief Animation Director</task><person id="15805">Kumi Ishii</person></staff>
<staff gid="657983527"><task>Sound Director</task><person id="2582">Toshiki Kameyama</person></staff>
<cast gid="2176791898" lang="EN"><role>Louise</role><person id="29102">Taylor Hannah</person></cast>
<cast gid="3086168368" lang="EN"><role>Edgar</role><person id="38660">Quentin Haag</person></cast>
<cast gid="1049677646" lang="EN"><role>Rose Sheedy</role><person id="44595">Brittney Karbowski</person></cast>
<cast gid="3301044640" lang="EN"><role>Kate Ashley</role><person id="53436">Melissa Davis</person></cast>
<cast gid="927928241" lang="EN"><role>Rachel Benning</role><person id="58058">Maggie Flecknoe</person></cast>
<cast gid="776278073" lang="EN"><role>Claire Forrest</role><person id="63337">Kara Greenberg</person></cast>
<cast gid="361978749" lang="JA"><role>Edgar</role><person id="662">Takehito Koyasu</person></cast>
<cast gid="3379701796" lang="JA"><role>Woman</role><person id="697">Rie Tanaka</person></cast>
<cast gid="2338380019" lang="JA"><role>Claire Forrest</role><person id="5735">Miyuki Sawashiro</person></cast>
<cast gid="3223408834" lang="JA"><role>Louise</role><person id="5916">Misato Fukuen</person></cast>
<cast gid="949341343" lang="JA"><role>Kate Ashley</role><person id="18645">Akira Tomisaka</person></cast>
<cast gid="1731162279" lang="JA"><role>Rachel Benning</role><person id="30284">Ryoko Shintani</person></cast>
<cast gid="1960723880" lang="JA"><role>Rose Sheedy</role><person id="42073">Ayumi Tsuji</person></cast>
<credit gid="3345044246"><task>Animation Production</task><company id="395">Gonzo</company></credit>
<credit gid="1851779782"><task>Production</task><company id="3083">Trinet Entertainment</company></credit></anime></ann>