<ann><anime id="854" gid="3154729312" type="TV" name="Gun Frontier" precision="TV" generated-on="2016-03-27T02:07:17Z">
<related-prev rel="related to" id="1238"/>
<info gid="2612386196" type="Picture" src="http://cdn.animenewsnetwork.com/thumbnails/fit200x200/encyc/A854-8.jpg" width="200" height="183"><img src="http://cdn.animenewsnetwork.com/thumbnails/fit200x200/encyc/A854-8.jpg" width="200" height="183"/><img src="http://cdn.animenewsnetwork.com/thumbnails/max500x600/encyc/A854-8.jpg" width="225" height="206"/></info>
<info gid="388109724" type="Main title" lang="EN">Gun Frontier</info>
<info gid="2347850340" type="Alternative title" lang="PT">Fronteira Sem Lei</info>
<info gid="3511962956" type="Alternative title" lang="ES">Frontera Sin Ley</info>
<info gid="1966485317" type="Alternative title" lang="ES">Frontera sin límites</info>
<info gid="808124732" type="Alternative title" lang="JA">ガンフロンティア</info>
<info gid="2112645300" type="Genres">action</info>
<info gid="2090055498" type="Genres">comedy</info>
<info gid="2485610093" type="Genres">drama</info>
<info gid="2051121792" type="Themes">western</info>
<info gid="1547015572" type="Objectionable content">TA</info>
<info gid="2495099332" type="Plot Summary">It is a harsh and barren wasteland, where the weak aren't allowed to dream. It is also a sacred land for true men, for there is no place a man can feel more alive. This is the Gun Frontier. Sea Pirate Captain Harlock and the errant samurai, Tochiro arrive in the United States on the Western Frontier. Along with a mysterious woman they meet along the way, the two friends challenge sex rings, bandits, and corrupt sheriff. They are searching for a lost clan of Japanese immigrants, and they will tear Gun Frontier from end to end until they find it.</info>
<info gid="410228128" type="Running time">25</info>
<info gid="2249584478" type="Number of episodes">13</info>
<info gid="1538444759" type="Vintage">2002-03-28 to 2002-06-20</info>
<info gid="3808426586" type="Vintage">2006-06-04 (HERO TV - Philippines)</info>
<info gid="1890763579" type="Vintage">2006-07-06 to 2006-09-28 (Animax Latin America)</info>
<info gid="2686864506" type="Vintage">2012-08-23 to 2012-09-13 (Mexico - Mixplay.tv)</info>
<info gid="980340793" type="Opening Theme">&quot;Style&quot; by Grand Zero</info>
<info gid="2279392852" type="Ending Theme">&quot;Ame to Sanbika (雨と賛美歌)&quot; by Umeno Yoshizawa</info>
<info gid="1754861135" type="Official website" lang="JA" href="http://enoki-films.co.jp/pro_gunfrontier.php">Enoki Films Gun Frontier Illusive Targets Website</info>
<ratings nb_votes="178" weighted_score="6.1052" bayesian_score="6.20169"/>
<episode num="1">
<title gid="1747071767" lang="EN">Departure to Gun Frontier</title></episode>
<episode num="2">
<title gid="1756245523" lang="EN">The Destruction of the Dry City</title></episode>
<episode num="3">
<title gid="1350124810" lang="EN">The Song of Horsemeat In A Sandstorm</title></episode>
<episode num="4">
<title gid="2584400489" lang="EN">Duel In The Rain</title></episode>
<episode num="5">
<title gid="1380319929" lang="EN">The Song of Bowlegs</title></episode>
<episode num="6">
<title gid="1984653764" lang="EN">Samurai Sword In A Deserted Land</title></episode>
<episode num="7">
<title gid="1619105101" lang="EN">The Bedroom Dream</title></episode>
<episode num="8">
<title gid="1586846669" lang="EN">The Wild Utamaro</title></episode>
<episode num="9">
<title gid="1311425390" lang="EN">A Duel Between Winchester And Midland City</title></episode>
<episode num="10">
<title gid="2195913395" lang="EN">The Midget In Misery</title></episode>
<episode num="11">
<title gid="2650193314" lang="EN">Matchlock In Jamacity</title></episode>
<episode num="12">
<title gid="1244308300" lang="EN">Shitalnen</title></episode>
<episode num="13">
<title gid="2645188151" lang="EN">Tracks Towards the Future</title></episode>
<release date="2003-04-29" href="http://www.animenewsnetwork.com/encyclopedia/releases.php?id=1167">Gun Frontier - Hopalong Harlock (DVD 1)</release>
<release date="2003-06-24" href="http://www.animenewsnetwork.com/encyclopedia/releases.php?id=1191">Gun Frontier - Midnight Samurai (DVD 2)</release>
<release date="2003-08-26" href="http://www.animenewsnetwork.com/encyclopedia/releases.php?id=1488">Gun Frontier - Nooses Wild (DVD 3)</release>
<release date="2003-10-28" href="http://www.animenewsnetwork.com/encyclopedia/releases.php?id=1611">Gun Frontier - Guns Blazing (DVD 4)</release>
<release date="2004-03-30" href="http://www.animenewsnetwork.com/encyclopedia/releases.php?id=2473">Gun Frontier - Complete Series (DVD 1-4)</release>
<news datetime="2002-08-14T16:41:33Z" href="http://www.animenewsnetwork.com/news/2002-08-14/enoki-films-updates-licenses">Enoki Films updates Licenses</news>
<staff gid="2677045753"><task>Director</task><person id="22267">Soichiro Zen</person></staff>
<staff gid="720193558"><task>Series Composition</task><person id="22260">Dr.Serial Nishioka</person></staff>
<staff gid="3819995724"><task>Script</task><person id="9401">Mugi Kamio</person></staff>
<staff gid="2533640142"><task>Storyboard</task><person id="22267">Soichiro Zen</person></staff>
<staff gid="2164387026"><task>Storyboard</task><person id="37632">Toshikatsu Tokoro</person></staff>
<staff gid="1604182590"><task>Storyboard</task><person id="65504">Hisato Shimoda</person></staff>
<staff gid="966173560"><task>Storyboard</task><person id="65993">Hiroyuki Shimazu</person></staff>
<staff gid="1494389877"><task>Storyboard</task><person id="99626">Noriko Kashima</person></staff>
<staff gid="1791817884"><task>Music</task><person id="15416">Hiroshi Motokura</person></staff>
<staff gid="1243895936"><task>Original Manga</task><person id="3138">Leiji Matsumoto</person></staff>
<staff gid="3132016023"><task>Character Design</task><person id="4087">Keisuke Masunaga</person></staff>
<staff gid="2198715045"><task>Character Design</task><person id="22261">Miho Nakata</person></staff>
<staff gid="3243342571"><task>Art Director</task><person id="17993">Makoto Dobashi</person></staff>
<staff gid="2935397831"><task>Animation Director</task><person id="5891">Ikuo Shimazu</person></staff>
<staff gid="3052163717"><task>Mechanical design</task><person id="14850">Katsumi Itabashi</person></staff>
<staff gid="2666359080"><task>Sound Director</task><person id="22262">Hiroyuki Hayase</person></staff>
<staff gid="1015186899"><task>Executive producer</task><person id="3346">Takaji Matsudo</person></staff>
<staff gid="1261265747"><task>Executive producer</task><person id="12128">Takayuki Yanagisawa</person></staff>
<staff gid="1791616405"><task>Executive producer</task><person id="17991">Akira Tsuburaya</person></staff>
<staff gid="3971921549"><task>Executive producer</task><person id="22257">Yoichi Machino</person></staff>
<staff gid="3640685108"><task>Executive producer</task><person id="22258">Yukio Terao</person></staff>
<staff gid="913331442"><task>Executive producer</task><person id="22259">Fueto Kikuchi</person></staff>
<staff gid="3231983769"><task>Producer</task><person id="17999">Tomoyuki Imai</person></staff>
<staff gid="2098556820"><task>Producer</task><person id="22264">Toshiharu Namiki</person></staff>
<staff gid="2034027805"><task>Producer</task><person id="22268">Akimoto Okagawa</person></staff>
<cast gid="2302422148" lang="EN"><role>Harlock</role><person id="539">David Lucas</person></cast>
<cast gid="995511483" lang="EN"><role>Tochiro</role><person id="3676">David Umansky</person></cast>
<cast gid="1115583989" lang="EN"><role>Shinonora</role><person id="14084">Kristy Pape</person></cast>
<cast gid="2413046470" lang="EN"><role>Shinohara</role><person id="15528">Kirsty Pape</person></cast>
<cast gid="1315799388" lang="ES"><role>Tochirou</role><person id="23442">Eduardo Garza</person></cast>
<cast gid="1853254398" lang="ES"><role>Harlock</role><person id="31035">Jose Luis Reza</person></cast>
<cast gid="2175605948" lang="JA"><role>Tochirou</role><person id="277">Kappei Yamaguchi</person></cast>
<cast gid="677930554" lang="JA"><role>Shizuku</role><person id="296">Chisa Yokoyama</person></cast>
<cast gid="2089502861" lang="JA"><role>Sinunora</role><person id="1172">Rica Matsumoto</person></cast>
<cast gid="1349403587" lang="JA"><role>Frank Harlock, Jr.</role><person id="6632">Eiji Takemoto</person></cast>
<cast gid="3018058565" lang="PT"><role>Frank Western Harlock Jr.</role><person id="48755">Sílvio Giraldi</person></cast>
<cast gid="3091805042" lang="PT"><role>Tochiro</role><person id="48757">Marcelo Campos</person></cast>
<cast gid="2131540601" lang="PT"><role>Sinunora</role><person id="48769">Marli Bortoleto</person></cast>
<cast gid="647640935" lang="PT"><role>Narrador</role><person id="48928">Antônio Moreno</person></cast>
<credit gid="3108599473"><task>Production</task><company id="262">TV Tokyo</company></credit>
<credit gid="1038448460"><task>Production</task><company id="514">Vega Entertainment</company></credit>
<credit gid="2837172456"><task>Production</task><company id="518">AT-X</company></credit>
<credit gid="1759714064"><task>Production</task><company id="1801">Tsuburaya Eizo</company></credit>
<credit gid="1951537714"><task>Production</task><company id="2148">Pronto</company></credit>
<credit gid="1046768251"><task>Production</task><company id="2149">Maczam</company></credit>
<credit gid="1270303157"><task>Production</task><company id="2426">Tsuburaya Productions Co., Ltd.</company></credit></anime></ann>